bot/__init__.py
bot/interface.py
bot/sublayers/address_book.py
bot/sublayers/cleaner.py
bot/sublayers/handler.py
bot/sublayers/notebook.py
GTTD-1.0.0.dist-info/LICENSE
GTTD-1.0.0.dist-info/METADATA
GTTD-1.0.0.dist-info/WHEEL
GTTD-1.0.0.dist-info/entry_points.txt
GTTD-1.0.0.dist-info/top_level.txt
GTTD-1.0.0.dist-info/RECORD
